nfselib_paulistana-0.3.0-nspkg.pth
nfselib/paulistana/__init__.py
nfselib/paulistana/docs/conf.py
nfselib/paulistana/docs/module_contents.txt
nfselib/paulistana/v02/PedidoCancelamentoLote.py
nfselib/paulistana/v02/PedidoCancelamentoNFe.py
nfselib/paulistana/v02/PedidoConsultaLote.py
nfselib/paulistana/v02/PedidoConsultaNFe.py
nfselib/paulistana/v02/PedidoEnvioLoteRPS.py
nfselib/paulistana/v02/RetornoCancelamentoNFe.py
nfselib/paulistana/v02/RetornoConsulta.py
nfselib/paulistana/v02/RetornoEnvioLoteRPS.py
nfselib/paulistana/v02/RetornoInformacoesLote.py
nfselib/paulistana/v02/__init__.py
nfselib/paulistana/v02/generatedsnamespaces.py
nfselib/paulistana/v03/PedidoCancelamentoLote.py
nfselib/paulistana/v03/PedidoCancelamentoNFe.py
nfselib/paulistana/v03/PedidoConsultaCNPJ.py
nfselib/paulistana/v03/PedidoConsultaLote.py
nfselib/paulistana/v03/PedidoConsultaNFe.py
nfselib/paulistana/v03/PedidoConsultaNFePeriodo.py
nfselib/paulistana/v03/PedidoEnvioLoteRPS.py
nfselib/paulistana/v03/PedidoEnvioRPS.py
nfselib/paulistana/v03/PedidoInformacoesLote.py
nfselib/paulistana/v03/RetornoCancelamentoNFe.py
nfselib/paulistana/v03/RetornoConsulta.py
nfselib/paulistana/v03/RetornoConsultaCNPJ.py
nfselib/paulistana/v03/RetornoEnvioLoteRPS.py
nfselib/paulistana/v03/RetornoEnvioRPS.py
nfselib/paulistana/v03/RetornoInformacoesLote.py
nfselib/paulistana/v03/__init__.py
nfselib/paulistana/v03/generatedsnamespaces.py
nfselib_paulistana-0.3.0.dist-info/AUTHORS.rst
nfselib_paulistana-0.3.0.dist-info/LICENSE
nfselib_paulistana-0.3.0.dist-info/METADATA
nfselib_paulistana-0.3.0.dist-info/WHEEL
nfselib_paulistana-0.3.0.dist-info/namespace_packages.txt
nfselib_paulistana-0.3.0.dist-info/top_level.txt
nfselib_paulistana-0.3.0.dist-info/RECORD
